python_rust_json_patch-0.1.5.dist-info/METADATA
python_rust_json_patch-0.1.5.dist-info/WHEEL
python_rust_json_patch/__init__.py
python_rust_json_patch/python_rust_json_patch.cpython-39-powerpc64le-linux-gnu.so
python_rust_json_patch-0.1.5.dist-info/RECORD
