Metadata-Version: 2.3
Name: python_rust_json_patch
Version: 0.1.5
Classifier: Programming Language :: Python :: 3
Classifier: License :: OSI Approved :: MIT License
Classifier: Operating System :: OS Independent
Summary: Rust json path wrapper
Author-email: Koca <admin@koca.win>
License: MIT
